tbot_mailing/__init__.py
tbot_mailing/admin.py
tbot_mailing/apps.py
tbot_mailing/models.py
tbot_mailing/tasks.py
tbot_mailing/migrations/__init__.py
django_tbot_mailing-0.1.1.dist-info/METADATA
django_tbot_mailing-0.1.1.dist-info/WHEEL
django_tbot_mailing-0.1.1.dist-info/top_level.txt
django_tbot_mailing-0.1.1.dist-info/RECORD
