Metadata-Version: 2.1
Name: django-tbot-mailing
Version: 0.1.1
Summary: Mailing function in your project
Home-page: https://gitlab.com/frv3r/django-tbot-mailing/
Author: frv3r
Author-email: daniil.marchenko@alpha-bots.com
License: MIT
Platform: UNKNOWN
Classifier: Intended Audience :: Developers
Classifier: License :: OSI Approved :: MIT License
Classifier: Operating System :: OS Independent
Classifier: Programming Language :: Python :: 3 :: Only
Classifier: Programming Language :: Python :: 3.10
Classifier: Programming Language :: Python :: Implementation :: CPython
Classifier: Topic :: Software Development :: Libraries :: Application Frameworks
Classifier: Topic :: Software Development :: Libraries :: Python Modules
Classifier: Framework :: Django :: 4.0
Requires-Dist: django-tbot-base (>=1.0.1)
Requires-Dist: Pillow (>=9.0.1)
Requires-Dist: celery (>=5.2.3)
